mira_sim/__init__.py
mira_sim/main.py
mira_sim/metrics/__init__.py
mira_sim/metrics/clap.py
mira_sim/metrics/coverid.py
mira_sim/metrics/defnet.py
mira_sim/metrics/kld.py
mira_sim/metrics/kldiv/audio_utils.py
mira_sim/metrics/kldiv/kld_metric.py
mira_sim-0.1.2.dist-info/COPYING
mira_sim-0.1.2.dist-info/METADATA
mira_sim-0.1.2.dist-info/WHEEL
mira_sim-0.1.2.dist-info/entry_points.txt
mira_sim-0.1.2.dist-info/top_level.txt
mira_sim-0.1.2.dist-info/RECORD
