Metadata-Version: 2.1
Name: mira-sim
Version: 0.1.2
Summary: MiRA tool is a model-independent open evaluation method based on four diverse audio music similarity metrics to assess exact data replication of the training set.
Maintainer-email: Roser Batlle-Roca <roser.batlle@upf.edu>
License: GNU AFFERO GENERAL PUBLIC LICENSE
Project-URL: Repository, https://github.com/roserbatlleroca/mira/
Requires-Python: >3.10
License-File: COPYING
Requires-Dist: pandas ==2.1.4
Requires-Dist: numpy ==1.23.5
Requires-Dist: essentia-tensorflow ==2.1b6.dev1110
Requires-Dist: scipy ==1.11.4
Requires-Dist: transformers ==4.30.2
Requires-Dist: laion-clap ==1.1.4
Requires-Dist: pydub ==0.25.1
Requires-Dist: torchmetrics ==1.2.1
Requires-Dist: julius ==0.2.7
